src/__init__.py
src/api.py
src/cli.py
src/normalize.py
src/far/classify/tokenize_and_classify.far
src/far/verbalize/verbalize.far
viet_itn-0.1.0.dist-info/METADATA
viet_itn-0.1.0.dist-info/WHEEL
viet_itn-0.1.0.dist-info/entry_points.txt
viet_itn-0.1.0.dist-info/licenses/LICENSE
viet_itn-0.1.0.dist-info/RECORD
