Metadata-Version: 2.4
Name: viet-itn
Version: 0.1.0
Summary: Vietnamese Inverse Text Normalizer
Author-email: Andrew <andrew@techainer.com>
License-File: LICENSE
Requires-Python: >=3.10
Requires-Dist: fastapi
Requires-Dist: pynini>=2.1.6.post1
Requires-Dist: uvicorn
